atera_client/__init__.py
atera_client/api_client.py
atera_client/configuration.py
atera_client/rest.py
atera_client/api/__init__.py
atera_client/api/agent_api.py
atera_client/api/alert_api.py
atera_client/api/billing_api.py
atera_client/api/contact_api.py
atera_client/api/contracts_api.py
atera_client/api/custom_values_api.py
atera_client/api/customer_api.py
atera_client/api/device_api.py
atera_client/api/knowledge_base_api.py
atera_client/api/rates_api.py
atera_client/api/ticket_api.py
atera_client/models/__init__.py
atera_client/models/agent_query_dto.py
atera_client/models/alert_query_dto.py
atera_client/models/api_result_wrapper_agent_query_dto.py
atera_client/models/api_result_wrapper_alert_query_dto.py
atera_client/models/api_result_wrapper_contact_query_dto.py
atera_client/models/api_result_wrapper_contract_query_dto.py
atera_client/models/api_result_wrapper_customer_query_dto.py
atera_client/models/api_result_wrapper_generic_device_query_dto.py
atera_client/models/api_result_wrapper_http_device_query_dto.py
atera_client/models/api_result_wrapper_invoice_query_dto.py
atera_client/models/api_result_wrapper_knowledge_base_query_dto.py
atera_client/models/api_result_wrapper_rate_query_dto.py
atera_client/models/api_result_wrapper_snmp_device_query_dto.py
atera_client/models/api_result_wrapper_tcp_device_query_dto.py
atera_client/models/api_result_wrapper_ticket_comment_query_dto.py
atera_client/models/api_result_wrapper_ticket_query_dto.py
atera_client/models/api_result_wrapper_ticket_time_entries_query_dto.py
atera_client/models/block_hours_contract_query_dto.py
atera_client/models/block_money_contract_query_dto.py
atera_client/models/contact_details.py
atera_client/models/contact_query_dto.py
atera_client/models/contacts_search_options.py
atera_client/models/contract_query_dto.py
atera_client/models/create_alert_dto.py
atera_client/models/create_contact_dto.py
atera_client/models/create_customer_attachment_dto.py
atera_client/models/create_customer_dto.py
atera_client-1.1.0.dist-info/METADATA
atera_client-1.1.0.dist-info/WHEEL
atera_client-1.1.0.dist-info/top_level.txt
atera_client-1.1.0.dist-info/RECORD
